scratchattachplus/__init__.py
scratchattachplus/scratchattachplus.py
scratchattachplus-0.4.0.dist-info/LICENSE
scratchattachplus-0.4.0.dist-info/METADATA
scratchattachplus-0.4.0.dist-info/WHEEL
scratchattachplus-0.4.0.dist-info/top_level.txt
scratchattachplus-0.4.0.dist-info/RECORD
