Metadata-Version: 2.1
Name: scratchattachplus
Version: 0.4.0
Summary: scratchattachの追加機能版
Home-page: https://github.com/kakeruzoku/scratchattachplus
Download-URL: https://github.com/kakeruzoku/scratchattachplus
Author: kakeruzoku
Author-email: kakeruzoku@gmail.com
Maintainer: kakeruzoku
Maintainer-email: kakeruzoku@gmail.com
License: MIT
Keywords: scratch api,scratchattach,scratch api python,scratch python,scratch for python,scratch,scratch cloud,scratch cloud variables,scratch bot
Classifier: Development Status :: 5 - Production/Stable
Classifier: Intended Audience :: Developers
Classifier: Programming Language :: Python :: 3
Classifier: Operating System :: Unix
Classifier: Operating System :: MacOS :: MacOS X
Classifier: Operating System :: Microsoft :: Windows
License-File: LICENSE
Requires-Dist: scratchattach
Requires-Dist: requests
